storagehandling/__init__.py
storagehandling/minio_handler.py
storagehandling/s3_handler.py
storagehandling/storage_handler.py
storagehandling-0.1.1.dist-info/METADATA
storagehandling-0.1.1.dist-info/WHEEL
storagehandling-0.1.1.dist-info/top_level.txt
storagehandling-0.1.1.dist-info/RECORD
