Metadata-Version: 2.1
Name: storagehandling
Version: 0.1.1
Summary: Library for storage handling
Home-page: UNKNOWN
Author: Shashi
Author-email: UNKNOWN
License: MIT
Platform: UNKNOWN
